setup.py
lplight/__init__.py
lplight/client.py
lplight/models.py
lplight.egg-info/PKG-INFO
lplight.egg-info/SOURCES.txt
lplight.egg-info/dependency_links.txt
lplight.egg-info/entry_points.txt
lplight.egg-info/requires.txt
lplight.egg-info/top_level.txt