Metadata-Version: 1.1
Name: lplight
Version: 0.0.2
Summary: Simple Launchpad client for retrieving project information and bugs
Home-page: https://github.com/jmvrbanac/lplight
Author: John Vrbanac
Author-email: john.vrbanac@linux.com
License: MIT
Keywords: launchpad lightweight client
Platform: UNKNOWN
Classifier: Development Status :: 3 - Alpha
Classifier: Intended Audience :: Developers
Classifier: License :: OSI Approved :: MIT License
Classifier: Programming Language :: Python :: 2.7
